custom_functions/__init__.py
custom_functions/ingest_data.py
custom_functions/modules.py
custom_functions/score.py
custom_functions/train.py
custom_functions-0.3.dist-info/METADATA
custom_functions-0.3.dist-info/WHEEL
custom_functions-0.3.dist-info/licenses/LICENCE
custom_functions-0.3.dist-info/RECORD
