Metadata-Version: 2.1
Name: custom_functions
Version: 0.3
Summary: A package for modules required for the Median housing value prediction
Author-email: TA-Davish <davish.balamurug@tigeranalytics.com>
License-File: LICENCE
Classifier: License :: OSI Approved :: MIT License
Classifier: Operating System :: OS Independent
Classifier: Programming Language :: Python :: 3
Requires-Python: >=3.7
